[
  {
    "title": "文化专题内容已更新",
    "brief": "平台已补充兰州牛肉面、城市文旅与非遗保护相关公开资料。",
    "content": "本次更新整理了公开来源中的饮食文化与文旅内容，现已同步到文化页与讲座关联阅读中，可用于课堂展示与毕设答辩演示。",
    "type": 0,
    "isTop": 1,
    "status": 1,
    "sourceName": "平台整理自公开资料",
    "sourceUrl": "https://www.gswbj.gov.cn/a/2024/02/22/19750.html",
    "publishedAt": "2026-04-19"
  },
  {
    "title": "活动报名支持手机号校验",
    "brief": "前台活动报名与下单链路已接入手机号绑定校验。",
    "content": "为保证活动报名、订单创建和个人资料信息完整，系统已将手机号授权作为关键业务节点的校验条件。",
    "type": 0,
    "isTop": 0,
    "status": 1,
    "sourceName": "平台功能更新",
    "sourceUrl": "",
    "publishedAt": "2026-04-19"
  },
  {
    "title": "新增规则推荐与讲座类型活动",
    "brief": "系统已新增规则推荐云函数，并支持在活动集合中区分讲座与普通活动。",
    "content": "推荐结果会优先参考用户收藏与订单行为，无历史记录时则回退到热门美食与文化内容，便于演示个性化推荐能力。",
    "type": 0,
    "isTop": 0,
    "status": 1,
    "sourceName": "平台功能更新",
    "sourceUrl": "",
    "publishedAt": "2026-04-19"
  }
]
